odoo9_addon_web_advanced_search_x2x-9.0.1.0.1-py2.7-nspkg.pth
odoo9_addon_web_advanced_search_x2x-9.0.1.0.1.dist-info/DESCRIPTION.rst
odoo9_addon_web_advanced_search_x2x-9.0.1.0.1.dist-info/METADATA
odoo9_addon_web_advanced_search_x2x-9.0.1.0.1.dist-info/RECORD
odoo9_addon_web_advanced_search_x2x-9.0.1.0.1.dist-info/WHEEL
odoo9_addon_web_advanced_search_x2x-9.0.1.0.1.dist-info/metadata.json
odoo9_addon_web_advanced_search_x2x-9.0.1.0.1.dist-info/namespace_packages.txt
odoo9_addon_web_advanced_search_x2x-9.0.1.0.1.dist-info/top_level.txt
odoo_addons/web_advanced_search_x2x/README.rst
odoo_addons/web_advanced_search_x2x/__init__.py
odoo_addons/web_advanced_search_x2x/__openerp__.py
odoo_addons/web_advanced_search_x2x/i18n/es.po
odoo_addons/web_advanced_search_x2x/i18n/fr.po
odoo_addons/web_advanced_search_x2x/i18n/nl.po
odoo_addons/web_advanced_search_x2x/i18n/web_advanced_search_x2x.pot
odoo_addons/web_advanced_search_x2x/static/description/icon.png
odoo_addons/web_advanced_search_x2x/static/src/css/web_advanced_search_x2x.less
odoo_addons/web_advanced_search_x2x/static/src/js/web_advanced_search_x2x.js
odoo_addons/web_advanced_search_x2x/static/src/xml/web_advanced_search_x2x.xml
odoo_addons/web_advanced_search_x2x/views/templates.xml
