Metadata-Version: 2.0
Name: odoo9-addon-web-advanced-search-x2x
Version: 9.0.1.0.1
Summary: Use a search widget in advanced search for x2x fields
Home-page: UNKNOWN
Author: Therp BV, Tecnativa, Odoo Community Association (OCA)
Author-email: support@odoo-community.org
License: AGPL-3
Platform: UNKNOWN
Classifier: Programming Language :: Python :: 2.7
Classifier: Framework :: Odoo
Classifier: License :: OSI Approved :: GNU Affero General Public License v3
Requires-Dist: odoo (<9.1a,>=9.0a)
